courierman/__init__.py
courierman/collection.py
courierman/folder.py
courierman/postman_entry.py
courierman/request.py
courierman-0.1.dist-info/METADATA
courierman-0.1.dist-info/WHEEL
courierman-0.1.dist-info/top_level.txt
courierman-0.1.dist-info/RECORD
