Metadata-Version: 2.1
Name: courierman
Version: 0.1
Summary: Courier Man - A Python interface for Postman
Home-page: https://github.com/cristianowa/courierman
Author: Cristiano W. Araujo
Author-email: cristianowerneraraujo@gmail.com
License: MIT
Download-URL: https://github.com/cristianowa/courierman/archive/0.1.zip
Keywords: postman
Platform: UNKNOWN
Classifier: License :: OSI Approved :: MIT License
Classifier: Programming Language :: Python :: 3
Classifier: Programming Language :: Python :: 3.7
Classifier: Programming Language :: Python :: 3.8
Classifier: Programming Language :: Python :: 3.9
Requires-Dist: requests
